README.rst
setup.py
pybrief/manage.py
pybrief.egg-info/PKG-INFO
pybrief.egg-info/SOURCES.txt
pybrief.egg-info/dependency_links.txt
pybrief.egg-info/not-zip-safe
pybrief.egg-info/requires.txt
pybrief.egg-info/top_level.txt