Metadata-Version: 1.1
Name: pybrief
Version: 1.0.1
Summary: PyBRIEF is a small blog system (and more cause it's
Home-page: https://github.com/bougie/pybrief
Author: David Hymonnet
Author-email: bougie@appartland.eu
License: BSD
Keywords: django blog bookmarks
Platform: UNKNOWN
Classifier: Development Status :: 4 - Beta
Classifier: License :: OSI Approved :: BSD License
Classifier: Programming Language :: Python :: 3
Classifier: Programming Language :: Python :: 3.3
Classifier: Programming Language :: Python :: 3.4
Classifier: Environment :: Web Environment
Classifier: Framework :: Django
Classifier: Framework :: Django :: 1.7
